gitid/main.py
gitid-0.2.5.data/scripts/gitid
gitid-0.2.5.dist-info/LICENSE
gitid-0.2.5.dist-info/METADATA
gitid-0.2.5.dist-info/WHEEL
gitid-0.2.5.dist-info/top_level.txt
gitid-0.2.5.dist-info/RECORD
