Metadata-Version: 2.1
Name: gitid
Version: 0.2.5
Summary: Command-line tool for managing multiple git identities on the same machine
Home-page: https://github.com/abhaybd/GitID
Author: Abhay Deshpande
Classifier: Programming Language :: Python :: 3
Classifier: License :: OSI Approved :: MIT License
Classifier: Operating System :: POSIX
Classifier: Environment :: Console
Classifier: Topic :: Software Development :: Version Control :: Git
Classifier: Topic :: Utilities
Classifier: Intended Audience :: Developers
License-File: LICENSE
Requires-Dist: PyYAML
